README.txt
setup.cfg
setup.py
Products/__init__.py
Products.OneTimeTokenPAS.egg-info/PKG-INFO
Products.OneTimeTokenPAS.egg-info/SOURCES.txt
Products.OneTimeTokenPAS.egg-info/dependency_links.txt
Products.OneTimeTokenPAS.egg-info/entry_points.txt
Products.OneTimeTokenPAS.egg-info/namespace_packages.txt
Products.OneTimeTokenPAS.egg-info/not-zip-safe
Products.OneTimeTokenPAS.egg-info/requires.txt
Products.OneTimeTokenPAS.egg-info/top_level.txt
Products/OneTimeTokenPAS/README
Products/OneTimeTokenPAS/__init__.py
Products/OneTimeTokenPAS/config.py
Products/OneTimeTokenPAS/configure.zcml
Products/OneTimeTokenPAS/login_as.pt
Products/OneTimeTokenPAS/login_as.py
Products/OneTimeTokenPAS/permissions.py
Products/OneTimeTokenPAS/tokenstorage.py
Products/OneTimeTokenPAS/version.txt
Products/OneTimeTokenPAS/Extensions/Install.py
Products/OneTimeTokenPAS/plugins/__init__.py
Products/OneTimeTokenPAS/plugins/onetimetoken_handler.py
Products/OneTimeTokenPAS/plugins/www/OneTimeTokenForm.dtml
Products/OneTimeTokenPAS/profiles/default/metadata.xml
Products/OneTimeTokenPAS/profiles/default/toolset.xml
Products/OneTimeTokenPAS/tests/__init__.py
Products/OneTimeTokenPAS/tests/test_tokenstorage.py
docs/HISTORY.txt