Metadata-Version: 1.0
Name: Products.OneTimeTokenPAS
Version: 0.3
Summary: Login using a token that can be only used once.
Home-page: UNKNOWN
Author: Kim Chee Leong
Author-email: leong at gw20e com
License: GPL
Keywords: Plone PAS plugin token
Platform: UNKNOWN
Classifier: Programming Language :: Python
Classifier: Topic :: Software Development :: Libraries :: Python Modules
